Workbook

Sheet FORMATO PRESUPUESTO GRAL
A1: FORMATO DE PRESUPUESTO 2026 INSTITUTO POBLANO DE LOS PUEBLOS INDÍGENAS UNIDAD DE TECNOLOGÍAS DE LA INFORMACIÓN
A3: EJERCICIO FISCAL | B3: PROGRAMA PRESUPUESTARIO | C3: CENTRO COSTOS | D3: ACTIVIDAD ESPECIFICA | E3: CLAVE PRESUPUESTAL | F3: CAPÍTULO | G3: PARTIDA ESPECIFICA | H3: NOMBRE DE PARTIDA | J3: NOMBRE DE PARTIDA | K3: RESTRINGIDA | L3: FUENTE DE FINANCIAMIENTO | M3: UR | N3: OBRA | O3: CONCEPTO DE OBRA | P3: PROGRAMA | Q3: COMPONENTE | R3: ACTIVIDAD | S3: TIPO DE GASTO | T3: TIPO DE PROYECTO | U3: REGION | V3: NOMBRE DE REGION | W3: MUNICIPIO | X3: NOMBRE DEL MUNICIPIO | Y3: REMANENTE DEL EJERCICIO | Z3: REGIONALIZACIÓN | AA3: IMPORTE | AB3: ENERO | AC3: FEBRERO | AD3: MARZO | AE3: ABRIL | AF3: MAYO | AG3: JUNIO | AH3: JULIO | AI3: AGOSTO | AJ3: SEPTIEMBRE | AK3: OCTUBRE | AL3: NOVIEMBRE | AM3: DICIEMBRE | AN3: TOTAL | AO3: JUSTIFICACIÓN
A4: 2026 | B4: E088 | C4: UNIDAD DE DESARROLLO DE TECNOLOGÍAS DE LA INFORMACIÓN | D4: 002 BIENES Y SERVICIOS CONSOLIDABLES | E4: 26-22-138-DA3Q-1-8-5-E088-00-200-1-5-1-115-002-2141-1-16-114-000000 | F4: =MID(E4,48,1) -> 2 | G4: =MID(E4,48,4) -> 2141 | H4: MATERIALES, ÚTILES Y EQUIPOS MENORES DE TECNOLOGÍAS DE LA INFORMACIÓN Y COMUNICACIONES | K4: NO | L4: 5.14 | M4: 0169 | N4: N/A | O4: N/A | P4: E088 | S4: 1 | T4: 00 | U4: =MID(E4,55,2) -> 16 | V4: PUEBLA CAPITAL | W4: =MID(E4,58,3) -> 114 | X4: PUEBLA | Y4: 0 | Z4: =CONCATENATE(U4, "-",W4, " ", X4) -> 16-114 PUEBLA | AA4: 65000 | AB4: 0 | AC4: 0 | AD4: 32500 | AE4: 0 | AF4: 0 | AG4: 32500 | AH4: 0 | AI4: 0 | AJ4: 0 | AK4: 0 | AL4: 0 | AM4: 0 | AN4: =SUM(AB4:AM4) -> 65000
A5: 2026 | B5: E088 | C5: UNIDAD DE DESARROLLO DE TECNOLOGÍAS DE LA INFORMACIÓN | D5: 004 GASTOS DE MANTENIMIENTO | E5: 26-22-138-DA3Q-1-8-5-E088-00-200-1-5-1-115-004-2941-1-16-114-000000 | F5: =MID(E5,48,1) -> 2 | G5: =MID(E5,48,4) -> 2941 | H5: REFACCIONES Y ACCESORIOS MENORES PARA EQUIPO DE CÓMPUTO Y TELECOMUNICACIONES | K5: NO | L5: 5.14 | M5: 0169 | N5: N/A | O5: N/A | P5: E088 | S5: 1 | T5: 00 | U5: =MID(E5,55,2) -> 16 | V5: PUEBLA CAPITAL | W5: =MID(E5,58,3) -> 114 | X5: PUEBLA | Y5: 0 | Z5: =CONCATENATE(U5, "-",W5, " ", X5) -> 16-114 PUEBLA | AA5: 71000 | AB5: 0 | AC5: 20000 | AD5: 0 | AE5: 11000 | AF5: 0 | AG5: 20000 | AH5: 0 | AI5: 0 | AJ5: 0 | AK5: 20000 | AL5: 0 | AM5: 0 | AN5: =SUM(AB5:AM5) -> 71000
A6: 2026 | B6: E088 | C6: UNIDAD DE DESARROLLO DE TECNOLOGÍAS DE LA INFORMACIÓN | D6: 003 GASTOS DE GESTIÓN ADMINISTRATIVA | E6: 26-22-138-DA3Q-1-8-5-E088-00-200-1-5-1-115-003-3363-1-16-114-000000 | F6: 3 | G6: 2151 | H6: MATERIAL IMPRESO E INFORMACIÓN DIGITAL | I6: 3363 | J6: SERVICIO DE IMPRESIÓN DE DOCUMENTOS Y PAPELERÍA OFICIAL | K6: NO | L6: 5.14 | M6: 0191 | N6: N/A | O6: N/A | P6: E088 | S6: 1 | T6: 00 | U6: =MID(E6,55,2) -> 16 | V6: PUEBLA CAPITAL | W6: =MID(E6,58,3) -> 114 | X6: PUEBLA | Y6: 0 | Z6: =CONCATENATE(U6, "-",W6, " ", X6) -> 16-114 PUEBLA | AA6: 10000 | AB6: 0 | AC6: 0 | AD6: 0 | AE6: 4000 | AF6: 500 | AG6: 0 | AH6: 4000 | AI6: 0 | AJ6: 1500 | AK6: 0 | AL6: 0 | AM6: 0 | AN6: =SUM(AB6:AM6) -> 10000
A7: 2026 | B7: E088 | C7: UNIDAD DE DESARROLLO DE TECNOLOGÍAS DE LA INFORMACIÓN | D7: 003 GASTOS DE GESTIÓN ADMINISTRATIVA | E7: 26-22-138-DA3Q-1-8-5-E088-00-200-1-5-1-115-003-3751-1-16-114-000000 | F7: =MID(E7,48,1) -> 3 | G7: =MID(E7,48,4) -> 3751 | H7: VIÁTICOS EN EL PAÍS | K7: NO | L7: 5.14 | M7: 0169 | N7: N/A | O7: N/A | P7: E088 | S7: 1 | T7: 00 | U7: =MID(E7,55,2) -> 16 | V7: #N/A | W7: =MID(E7,58,3) -> 114 | X7: PUEBLA | Y7: 0 | Z7: =CONCATENATE(U7, "-",W7, " ", X7) -> 16-114 PUEBLA | AA7: 10000 | AB7: 0 | AC7: 500 | AD7: 800 | AE7: 1000 | AF7: 800 | AG7: 1000 | AH7: 1400 | AI7: 900 | AJ7: 1300 | AK7: 1200 | AL7: 1100 | AM7: 0 | AN7: =SUM(AB7:AM7) -> 10000
A8: 2026 | B8: E088 | C8: UNIDAD DE DESARROLLO DE TECNOLOGÍAS DE LA INFORMACIÓN | D8: 003 GASTOS DE GESTIÓN ADMINISTRATIVA | E8: 26-22-138-DA3Q-1-8-5-E088-00-200-1-5-1-115-003-3792-1-16-114-000000 | F8: 3 | G8: 3792 | H8: GASTOS PARA OPERATIVOS Y TRABAJOS DE CAMPO EN ÁREAS RURALES | K8: NO | L8: 5.14 | M8: 0169 | N8: N/A | O8: N/A | P8: E088 | S8: 1 | T8: 00 | U8: 21 | V8: #N/A | W8: 114 | X8: PUEBLA | Y8: 0 | Z8: 21-114 PUEBLA | AA8: 15000 | AB8: 0 | AC8: 1500 | AD8: 2000 | AE8: 1500 | AF8: 1500 | AG8: 1500 | AH8: 1500 | AI8: 1500 | AJ8: 1500 | AK8: 1000 | AL8: 500 | AM8: 1000 | AN8: =SUM(AB8:AM8) -> 15000
A9: 2026 | B9: E088 | C9: UNIDAD DE DESARROLLO DE TECNOLOGÍAS DE LA INFORMACIÓN | D9: 003 GASTOS DE GESTIÓN ADMINISTRATIVA | E9: 26-22-138-DA3Q-1-8-5-E088-00-200-1-5-1-115-003-3921-1-16-114-000000 | F9: =MID(E9,48,1) -> 3 | G9: =MID(E9,48,4) -> 3921 | H9: OTROS IMPUESTOS Y DERECHOS | K9: NO | L9: 5.14 | M9: 0169 | N9: N/A | O9: N/A | P9: E088 | S9: 1 | T9: 00 | U9: =MID(E9,55,2) -> 16 | V9: #N/A | W9: =MID(E9,58,3) -> 114 | X9: PUEBLA | Y9: 0 | Z9: =CONCATENATE(U9, "-",W9, " ", X9) -> 16-114 PUEBLA | AA9: 10000 | AB9: 0 | AC9: 500 | AD9: 1000 | AE9: 1200 | AF9: 1500 | AG9: 1000 | AH9: 1000 | AI9: 500 | AJ9: 1000 | AK9: 1000 | AL9: 800 | AM9: 500 | AN9: =SUM(AB9:AM9) -> 10000
AB10: =SUBTOTAL(9,AB4:AB9) -> 0 | AC10: =SUBTOTAL(9,AC4:AC9) -> 22500 | AD10: =SUBTOTAL(9,AD4:AD9) -> 36300 | AE10: =SUBTOTAL(9,AE4:AE9) -> 18700 | AF10: =SUBTOTAL(9,AF4:AF9) -> 4300 | AG10: =SUBTOTAL(9,AG4:AG9) -> 56000 | AH10: =SUBTOTAL(9,AH4:AH9) -> 7900 | AI10: =SUBTOTAL(9,AI4:AI9) -> 2900 | ... AN10: =SUBTOTAL(9,AN4:AN9) -> 181000

Sheet GASTOS
A1: TOTALES | C1: ='FORMATO PRESUPUESTO GRAL'!AN4 -> 65000 | D1: ='FORMATO PRESUPUESTO GRAL'!AN5 -> 71000 | E1: ='FORMATO PRESUPUESTO GRAL'!AN6 -> 10000 | F1: ='FORMATO PRESUPUESTO GRAL'!AN7 -> 10000 | G1: ='FORMATO PRESUPUESTO GRAL'!AN8 -> 15000 | H1: ='FORMATO PRESUPUESTO GRAL'!AN9 -> 10000 | I1: =SUM(C1:H1) -> 181000
A2: GASTADO | C2: =SUM(Tabla1[2141]) -> 32472.52 | D2: =SUM(Tabla1[2941]) -> 30563.74 | E2: =SUM(Tabla1[2151]) -> 0 | F2: =SUM(Tabla1[3751]) -> 0 | G2: =SUM(Tabla1[3792]) -> 1005 | H2: =SUM(Tabla1[3921]) -> 596 | I2: =SUM(C2:H2) -> 64637.26
A3: DISPONIBLE | C3: =C1-C2 -> 32527.48 | D3: =D1-D2 -> 40436.26 | E3: =E1-E2 -> 10000 | F3: =F1-F2 -> 10000 | G3: =G1-G2 -> 13995 | H3: =H1-H2 -> 9404 | I3: =SUM(C3:H3) -> 116362.74
A5: OFICIO | B5: FECHA | C5: 2141 | D5: 2941 | E5: 2151 | F5: 3751 | G5: 3792 | H5: 3921 | I5: Resposable | J5: OBJ
A6: SDTI/003/2026 | B6: 46135 | G6: 1005 | H6: 596 | I6: Moises Ismael Rosas Cabrera
A7: IPPI/SDTI/003/2026 | B7: 46153 | C7: 32472.52 | I7: Moises Ismael Rosas Cabrera
A8: IPPI/SDTI/004/2026 | B8: 46153 | D8: 30563.74 | I8: Moises Ismael Rosas Cabrera
