Workbook

Sheet FORMATO PRESUPUESTO GRAL
A1: FORMATO DE PRESUPUESTO 2027 INSTITUTO POBLANO DE LOS PUEBLOS INDÍGENAS
A3: EJERCICIO FISCAL | B3: PROGRAMA PRESUPUESTARIO | C3: CENTRO COSTOS | D3: NUMERO DE ACTIVIDAD ESPECIFICA | E3: ACTIVIDAD ESPECIFICA | F3: CLAVE PRESUPUESTAL | G3: CAPÍTULO | H3: PARTIDA ESPECIFICA | I3: NOMBRE DE PARTIDA | J3: RESTRINGIDA | K3: FUENTE DE FINANCIAMIENTO | L3: UR | M3: OBRA | N3: CONCEPTO DE OBRA | O3: PROGRAMA | P3: COMPONENTE | Q3: ACTIVIDAD | R3: TIPO DE GASTO | S3: TIPO DE PROYECTO | T3: REGION | U3: NOMBRE DE REGION | V3: MUNICIPIO | W3: NOMBRE DEL MUNICIPIO | X3: REMANENTE DEL EJERCICIO | Y3: REGIONALIZACIÓN | Z3: IMPORTE | AA3: ENERO | AB3: FEBRERO | AC3: MARZO | AD3: ABRIL | AE3: MAYO | AF3: JUNIO | AG3: JULIO | AH3: AGOSTO | AI3: SEPTIEMBRE | AJ3: OCTUBRE | AK3: NOVIEMBRE | AL3: DICIEMBRE | AM3: TOTAL | AN3: JUSTIFICACIÓN
A4: 2027 | B4: E088 | C4: SUBDIRECCIÓN DE DESARROLLO DE TECNOLOGÍAS DE LA INFORMACIÓN | D4: =MID(F4,44,3) -> 002 | E4: BIENES Y SERVICIOS CONSOLIDABLES | F4: 26-22-138-DA3Q-1-8-5-E088-00-200-1-5-1-115-002-2141-1-16-114-000000 | G4: =MID(F4,48,1) -> 2 | H4: =MID(F4,48,4) -> 2141 | I4: MATERIALES, ÚTILES Y EQUIPOS MENORES DE TECNOLOGÍAS DE LA INFORMACIÓN Y COMUNICACIONES | J4: NO | K4: 5.14 | L4: 0169 | M4: N/A | N4: N/A | O4: E088 | R4: 1 | S4: 00 | T4: =MID(F4,55,2) -> 16 | U4: =VLOOKUP(T4,'CATALOGO DE REGIONES'!B$2:C$28,2,FALSE) -> PUEBLA CAPITAL | V4: =MID(F4,58,3) -> 114 | W4: PUEBLA | X4: 0 | Y4: =CONCATENATE(T4, "-",V4, " ", W4) -> 16-114 PUEBLA | Z4: 80000 | AA4: 0 | AB4: 0 | AC4: 40000 | AD4: 0 | AE4: 0 | AF4: 40000 | AG4: 0 | AH4: 0 | AI4: 0 | AJ4: 0 | AK4: 0 | AL4: 0 | AM4: =SUM(AA4:AL4) -> 80000 | AN4: Los recursos de esta partida se destinan a la adquisición de kits de desarrollo electrónico con microcontrolador, tableta de prototipado y conjunto de sensores, distribuidos en partes iguales entre los Módulos Interculturales Digitales del Instituto, ubicados en los municipios de Cuautempan, Eloxochitlán y San Gabriel Chilac; así como a la compra de componentes electrónicos de reposición, módulos de sensores complementarios e instrumentos menores de medición y ensamble necesarios para la operación de los talleres. El equipamiento permanece bajo resguardo de cada Módulo al concluir el ejercicio, de modo que la inversión no se agota en una sola generación de participantes, sino que habilita a los Módulos para impartir formación tecnológica de manera recurrente en ejercicios posteriores. La adquisición encuentra fundamento en el artículo 21, fracciones VII, IX, XI y XII del Reglamento Interior del Instituto Poblano de los Pueblos Indígenas, que facultan a la Subdirección de Desarrollo de Tecnologías de la Información para impulsar cursos y talleres orientados las pueblos y comunidades indígenas en tecnologías de la información, gestionar la implementación de los Módulos Interculturales Digitales con pertinencia cultural y lingüística; y promover su establecimiento mediante programas y proyectos que impulsen su uso, acceso y apropiación. Se vincula con el artículo 85, fracciones X, XXX y XLII de la Ley de Derechos, Cultura y Desarrollo de los Pueblos y Comunidades Indígenas del Estado de Puebla, relativas a la atención de las juventudes indígenas, al desarrollo de programas de formación y capacitación, y al fortalecimiento de la educación indígena. El resultado esperado es la formación de jóvenes de nivel medio superior en fundamentos de electrónica, programación de microcontroladores y aplicación de sensores.
A5: 2027 | B5: E088 | C5: SUBDIRECCIÓN DE DESARROLLO DE TECNOLOGÍAS DE LA INFORMACIÓN | D5: =MID(F5,44,3) -> 004 | E5: GASTOS DE MANTENIMIENTO | F5: 26-22-138-DA3Q-1-8-5-E088-00-200-1-5-1-115-004-2941-1-16-114-000000 | G5: =MID(F5,48,1) -> 2 | H5: =MID(F5,48,4) -> 2941 | I5: REFACCIONES Y ACCESORIOS MENORES PARA EQUIPO DE CÓMPUTO Y TELECOMUNICACIONES | J5: NO | K5: 5.14 | L5: 0169 | M5: N/A | N5: N/A | O5: E088 | R5: 1 | S5: 00 | T5: =MID(F5,55,2) -> 16 | U5: =VLOOKUP(T5,'CATALOGO DE REGIONES'!B$2:C$28,2,FALSE) -> PUEBLA CAPITAL | V5: =MID(F5,58,3) -> 114 | W5: PUEBLA | X5: 0 | Y5: =CONCATENATE(T5, "-",V5, " ", W5) -> 16-114 PUEBLA | Z5: 75000 | AA5: 0 | AB5: 20000 | AC5: 0 | AD5: 15000 | AE5: 0 | AF5: 15000 | AG5: 0 | AH5: 15000 | AI5: 0 | AJ5: 10000 | AK5: 0 | AL5: 0 | AM5: =SUM(AA5:AL5) -> 75000 | AN5: Esta partida cubre la adquisición de refacciones, accesorios y componentes menores requeridos para mantener en operación el equipo de cómputo y de telecomunicaciones instalado en los Módulos Interculturales Digitales, así como el equipo de cómputo del instituto para su operatividad. Comprende fuentes de poder, unidades de almacenamiento, módulos de memoria, dispositivos periféricos, reguladores y respaldos de energía, cableado estructurado, dispositivos de red, adaptadores y elementos de conectividad. Los Módulos se encuentran en localidades de sierra, expuestos a condiciones de humedad, variaciones de temperatura y suministro eléctrico irregular, lo que acelera el desgaste de los componentes y hace del mantenimiento correctivo una condición necesaria para que los espacios permanezcan funcionales. El gasto se sustenta en el artículo 21, fracciones I, II y III del Reglamento Interior, que atribuyen a esta Subdirección la coordinación de la aplicación de los sistemas informáticos y el equipamiento correspondiente en todas las unidades administrativas, la gestión de los medios informáticos, tecnológicos y de telecomunicaciones para el alcance de los objetivos institucionales, y la dirección de los procesos de mantenimiento preventivo, correctivo y de actualización de la infraestructura tecnológica. Corresponde igualmente a las funciones 7 y 10 de la Subdirección y a las funciones 3 y 5 del Departamento de Tecnologías de la Información establecidas en el Manual de Organización, relativas a la ejecución del mantenimiento y a la emisión de dictámenes técnicos sobre el estado físico u obsolescencia de los bienes informáticos. El resultado esperado es la continuidad operativa del Instituto y de los Módulos durante todo el ejercicio, en condición indispensable para impartir en ellos el programa de formación tecnológica y para que puedan prestar servicio a la población de sus comunidades el resto del año. La disponibilidad de los equipos es además el insumo que permitirá documentar el nivel de uso y funcionalidad de los Módulos, evidencia con la que el Instituto sustentará la conveniencia de ampliar el número de espacios en ejercicios posteriores, conforme al artículo 85, fracción XLIII de la Ley, referido a la creación y rehabilitación de espacios dignos para la atención integral e intercultural de las juventudes indígenas.
A6: 2027 | B6: E088 | C6: SUBDIRECCIÓN DE DESARROLLO DE TECNOLOGÍAS DE LA INFORMACIÓN | D6: =MID(F6,44,3) -> 003 | E6: GASTOS DE GESTIÓN ADMINISTRATIVA | F6: 26-22-138-DA3Q-1-8-5-E088-00-200-1-5-1-115-003-2151-1-16-114-000000 | G6: 3 | H6: =MID(F6,48,4) -> 2151 | I6: MATERIAL IMPRESO E INFORMACIÓN DIGITAL | J6: NO | K6: 5.14 | L6: 0191 | M6: N/A | N6: N/A | O6: E088 | R6: 1 | S6: 00 | T6: =MID(F6,55,2) -> 16 | U6: =VLOOKUP(T6,'CATALOGO DE REGIONES'!B$2:C$28,2,FALSE) -> PUEBLA CAPITAL | V6: =MID(F6,58,3) -> 114 | W6: PUEBLA | X6: 0 | Y6: =CONCATENATE(T6, "-",V6, " ", W6) -> 16-114 PUEBLA | Z6: 15000 | AA6: 0 | AB6: 6000 | AC6: 0 | AD6: 0 | AE6: 3000 | AF6: 0 | AG6: 3000 | AH6: 0 | AI6: 3000 | AJ6: 0 | AK6: 0 | AL6: 0 | AM6: =SUM(AA6:AL6) -> 15000 | AN6: El recurso se destina a la producción del material documental del programa de formación: lonas, banners, manual del curso, cuadernillos de práctica y ejercicios para las sesiones presenciales, constancias de participación para las personas que concluyan el programa, señalética de identificación de los talleres en cada Módulo, y la elaboración de las versiones digitales descargables de dichos materiales para su consulta posterior por parte de las comunidades. La pertinencia lingüística de estos materiales no es un elemento decorativo: los municipios sede son municipios indígenas y hablantes de lenguas originarias náhuatl y popoloca.
A7: 2027 | B7: E088 | C7: SUBDIRECCIÓN DE DESARROLLO DE TECNOLOGÍAS DE LA INFORMACIÓN | D7: =MID(F7,44,3) -> 003 | E7: GASTOS DE GESTIÓN ADMINISTRATIVA | F7: 26-22-138-DA3Q-1-8-5-E088-00-200-1-5-1-115-003-3751-1-16-114-000000 | G7: =MID(F7,48,1) -> 3 | H7: =MID(F7,48,4) -> 3751 | I7: VIÁTICOS EN EL PAÍS | J7: NO | K7: 5.14 | L7: 0169 | M7: N/A | N7: N/A | O7: E088 | R7: 1 | S7: 00 | T7: =MID(F7,55,2) -> 16 | U7: =VLOOKUP(T7,'CATALOGO DE REGIONES'!B$2:C$28,2,FALSE) -> PUEBLA CAPITAL | V7: =MID(F7,58,3) -> 114 | W7: PUEBLA | X7: 0 | Y7: =CONCATENATE(T7, "-",V7, " ", W7) -> 16-114 PUEBLA | Z7: 15000 | AA7: 0 | AB7: 1500 | AC7: 1500 | AD7: 1500 | AE7: 1500 | AF7: 1500 | AG7: 1500 | AH7: 1500 | AI7: 1500 | AJ7: 1500 | AK7: 1500 | AL7: 0 | AM7: =SUM(AA7:AL7) -> 15000 | AN7: Esta partida cubre los gastos de hospedaje y alimentación que cuentan con comprobante fiscal, erogados por el personal de la Subdirección de Desarrollo de Tecnologías de la Información durante las comisiones a los Módulos Interculturales Digitales del Instituto. El desplazamiento con pernocta es una condición primordial del programa y no una preferencia operativa. Los Módulos se localizan en la Sierra Norte, la Sierra Negra y la región de Tehuacán, a distancias que impiden trasladarse, impartir una jornada completa de trabajo y regresar el mismo día. Sin la cobertura de hospedaje, la capacitación tendría que reducirse a sesiones de pocas horas por visita, insuficientes para un taller de electrónica que requiere trabajo continuo con equipo. El resultado esperado es la ejecución de las comisiones y la impartición completa del programa a los jóvenes.
A8: 2027 | B8: E088 | C8: SUBDIRECCIÓN DE DESARROLLO DE TECNOLOGÍAS DE LA INFORMACIÓN | D8: =MID(F8,44,3) -> 003 | E8: GASTOS DE GESTIÓN ADMINISTRATIVA | F8: 26-22-138-DA3Q-1-8-5-E088-00-200-1-5-1-115-003-3792-1-16-114-000000 | G8: 3 | H8: 3792 | I8: GASTOS PARA OPERATIVOS Y TRABAJOS DE CAMPO EN ÁREAS RURALES | J8: NO | K8: 5.14 | L8: 0169 | M8: N/A | N8: N/A | O8: E088 | R8: 1 | S8: 00 | T8: 21 | U8: =VLOOKUP(T8,'CATALOGO DE REGIONES'!B$2:C$28,2,FALSE) -> ATLIXCO | V8: 114 | W8: PUEBLA | X8: 0 | Y8: 21-114 PUEBLA | Z8: 25000 | AA8: 0 | AB8: 2500 | AC8: 2500 | AD8: 2500 | AE8: 2500 | AF8: 2500 | AG8: 2500 | AH8: 2500 | AI8: 2500 | AJ8: 2500 | AK8: 2500 | AL8: 0 | AM8: =SUM(AA8:AL8) -> 25000 | AN8: Esta partida cubre la alimentación, el transporte local y las erogaciones menores del personal comisionado durante los trabajos de campo en los Módulos Interculturales Digitales, correspondientes a los conceptos que por las condiciones del lugar no pueden ampararse con comprobante fiscal. Comprende los alimentos adquiridos en establecimientos y mercados comunitarios de las localidades sede, el transporte local entre la cabecera municipal y la localidad donde se ubica el Módulo, y los gastos de camino propios de la operación en zonas de sierra. En las localidades sede la actividad comercial se desarrolla de manera predominantemente informal y no existen establecimientos que expidan comprobantes fiscales, por lo que estos conceptos se comprueban conforme a las disposiciones aplicables a los gastos de camino en comisiones oficiales. La denominación de la partida contempla expresamente los operativos y trabajos de campo en áreas rurales, que es la condición en la que se desarrolla la totalidad de este programa.
A9: 2027 | B9: E088 | C9: SUBDIRECCIÓN DE DESARROLLO DE TECNOLOGÍAS DE LA INFORMACIÓN | D9: =MID(F9,44,3) -> 003 | E9: GASTOS DE GESTIÓN ADMINISTRATIVA | F9: 26-22-138-DA3Q-1-8-5-E088-00-200-1-5-1-115-003-3921-1-16-114-000000 | G9: =MID(F9,48,1) -> 3 | H9: =MID(F9,48,4) -> 3921 | I9: OTROS IMPUESTOS Y DERECHOS | J9: NO | K9: 5.14 | L9: 0169 | M9: N/A | N9: N/A | O9: E088 | R9: 1 | S9: 00 | T9: =MID(F9,55,2) -> 16 | U9: =VLOOKUP(T9,'CATALOGO DE REGIONES'!B$2:C$28,2,FALSE) -> PUEBLA CAPITAL | V9: =MID(F9,58,3) -> 114 | W9: PUEBLA | X9: 0 | Y9: =CONCATENATE(T9, "-",V9, " ", W9) -> 16-114 PUEBLA | Z9: 15000 | AA9: 0 | AB9: 1500 | AC9: 1500 | AD9: 1500 | AE9: 1500 | AF9: 1500 | AG9: 1500 | AH9: 1500 | AI9: 1500 | AJ9: 1500 | AK9: 1500 | AL9: 0 | AM9: =SUM(AA9:AL9) -> 15000 | AN9: Esta partida se destina al pago de los derechos por uso de vías de cuota, es decir, las casetas de peaje correspondientes a los trayectos de ida y retorno de las comisiones programadas hacia los Módulos Interculturales Digitales. Los recorridos parten de la sede del Instituto en la ciudad de Puebla hacia las comunidades indígenas. El uso de las vías de cuota responde a condiciones de seguridad y de aprovechamiento del tiempo de comisión. Las rutas libres hacia ambas sierras incrementan de manera considerable los tiempos de traslado y reducen las horas efectivas disponibles para impartir los talleres dentro de una comisión de tres días. Prescindir de esta previsión obligaría a extender la duración de cada comisión, con el consecuente aumento del gasto en viáticos, o bien a recortar las horas de formación impartidas a las personas participantes.

Sheet CATALOGO DE PARTIDAS
A1: EJERCICIO FISCAL | B1: CAPÍTULO | C1: CONCEPTO | D1: PARTIDA GENÉRICA | E1: PARTIDA ESPECÍFICA | F1: DESCRIPCIÓN | G1: CONCEPTO RESTRINGIDO | H1: ESTATUS
A2: 2026 | B2: 2000 | C2: 2100 | D2: 2110 | E2: 2111 | F2: MATERIALES, ÚTILES Y EQUIPOS MENORES DE OFICINA | G2: NO | H2: A
A3: 2026 | B3: 2000 | C3: 2100 | D3: 2120 | E3: 2121 | F3: MATERIALES Y ÚTILES DE IMPRESIÓN Y REPRODUCCIÓN | G3: NO | H3: A
A4: 2026 | B4: 2000 | C4: 2100 | D4: 2130 | E4: 2131 | F4: MATERIAL ESTADÍSTICO Y GEOGRÁFICO | G4: NO | H4: A
A5: 2026 | B5: 2000 | C5: 2100 | D5: 2140 | E5: 2141 | F5: MATERIALES, ÚTILES Y EQUIPOS MENORES DE TECNOLOGÍAS DE LA INFORMACIÓN Y COMUNICACIONES | G5: NO | H5: A
A6: 2026 | B6: 2000 | C6: 2100 | D6: 2150 | E6: 2151 | F6: MATERIAL IMPRESO E INFORMACIÓN DIGITAL | G6: NO | H6: A
A7: 2026 | B7: 2000 | C7: 2100 | D7: 2160 | E7: 2161 | F7: MATERIAL DE LIMPIEZA | G7: NO | H7: A
A8: 2026 | B8: 2000 | C8: 2100 | D8: 2170 | E8: 2171 | F8: MATERIALES Y ÚTILES DE ENSEÑANZA | G8: NO | H8: A
A9: 2026 | B9: 2000 | C9: 2100 | D9: 2180 | E9: 2181 | F9: REGISTRO E IDENTIFICACIÓN DE BIENES Y PERSONAS | G9: NO | H9: A
A10: 2026 | B10: 2000 | C10: 2100 | D10: 2180 | E10: 2182 | F10: REGISTRO E IDENTIFICACIÓN VEHICULAR | G10: NO | H10: A
A11: 2026 | B11: 2000 | C11: 2100 | D11: 2180 | E11: 2183 | F11: ADQUISICIÓN DE FORMAS VALORADAS | G11: NO | H11: A
A12: 2026 | B12: 2000 | C12: 2200 | D12: 2210 | E12: 2211 | F12: PRODUCTOS ALIMENTICIOS PARA LOS EFECTIVOS QUE PARTICIPEN EN PROGRAMAS DE SEGURIDAD PÚBLICA | G12: NO | H12: A
A13: 2026 | B13: 2000 | C13: 2200 | D13: 2210 | E13: 2212 | F13: PRODUCTOS ALIMENTICIOS PARA LOS EFECTIVOS QUE REALICEN LABORES EN CAMPO O DE SUPERVISIÓN | G13: NO | H13: A
... A288: 2026 | B288: 5000 | C288: 5900 | D288: 5990 | E288: 5991 | F288: OTROS ACTIVOS INTANGIBLES | G288: NO | H288: A

Sheet CATALOGO DE ACTIVIDADES
A1: EJERCICIO FISCAL | B1: RAMO | C1: ACTIVIDAD ESPECÍFICA | D1: DESCRIPCIÓN | E1: ESTATUS
A2: 2026 | B2: 22 | C2: 000 | D2: NO ASOCIADO A CONCEPTO | E2: A
A3: 2026 | B3: 22 | C3: 001 | D3: SERVICIOS BÁSICOS | E3: A
A4: 2026 | B4: 22 | C4: 002 | D4: BIENES Y SERVICIOS CONSOLIDABLES | E4: A
A5: 2026 | B5: 22 | C5: 003 | D5: GASTOS DE GESTIÓN ADMINISTRATIVA | E5: A
A6: 2026 | B6: 22 | C6: 004 | D6: GASTOS DE MANTENIMIENTO | E6: A
A7: 2026 | B7: 22 | C7: 005 | D7: AUDITOR EXTERNO | E7: A
A8: 2026 | B8: 22 | C8: 006 | D8: DIFUSIÓN Y TRANSMISIÓN DEL DOCUMENTAL | E8: I
A9: 2026 | B9: 22 | C9: 007 | D9: COMUNICACIÓN SOCIAL | E9: A
A10: 2026 | B10: 22 | C10: 008 | D10: ARRENDAMIENTO DE VEHÍCULOS | E10: A
A11: 2026 | B11: 22 | C11: 009 | D11: TRANSMISIÓN DE CONTENIDOS EDUCATIVOS, CULTURALES Y NOTICIOSOS | E11: A
A12: 2026 | B12: 22 | C12: 012 | D12: COMPENSACIÓN COMPLEMENTARIA | E12: A
A13: 2026 | B13: 22 | C13: 017 | D13: ESTRATEGIAS DE INFORMACIÓN, DIFUSIÓN Y CONECTIVIDAD | E13: I
... A28: 2026 | B28: 22 | C28: 188 | D28: SERVICIO INTEGRAL FUNERARIO | E28: A

Sheet CATALOGO DE TIPO DE GASTO
A1: EJERCICIO FISCAL | B1: TIPO GASTO | C1: DESCRIPCIÓN | D1: ESTATUS
A2: 2026 | B2: 1 | C2: GASTO CORRIENTE | D2: A
A3: 2026 | B3: 2 | C3: GASTO DE CAPITAL | D3: A
A4: 2026 | B4: 3 | C4: AMORTIZACIÓN DE LA DEUDA Y DISMINUCIÓN DE PASIVOS | D4: A
A5: 2026 | B5: 4 | C5: PENSIONES Y JUBILACIONES | D5: A
A6: 2026 | B6: 5 | C6: PARTICIPACIONES | D6: A

Sheet CATALOGO DE CAPITULOS
A1: EJERCICIO FISCAL | B1: CAPÍTULO | C1: DESCRIPCIÓN | D1: ESTATUS
A2: 2026 | B2: 2000 | C2: MATERIALES Y SUMINISTROS | D2: A
A3: 2026 | B3: 3000 | C3: SERVICIOS GENERALES | D3: A
A4: 2026 | B4: 4000 | C4: TRANSFERENCIAS, ASIGNACIONES, SUBSIDIOS Y OTRAS AYUDAS | D4: A
A5: 2026 | B5: 5000 | C5: BIENES MUEBLES, INMUEBLES E INTANGIBLES | D5: A

Sheet CATALOGO DE MUNICIPIOS
A1: EJERCICIO FISCAL | B1: ESTADO | C1: MUNICIPIO | D1: DESCRIPCIÓN | E1: ESTATUS
A2: 2026 | B2: 21 | C2: 001 | D2: ACAJETE | E2: A
A3: 2026 | B3: 21 | C3: 002 | D3: ACATENO | E3: A
A4: 2026 | B4: 21 | C4: 003 | D4: ACATLÁN | E4: A
A5: 2026 | B5: 21 | C5: 004 | D5: ACATZINGO | E5: A
A6: 2026 | B6: 21 | C6: 005 | D6: ACTEOPAN | E6: A
A7: 2026 | B7: 21 | C7: 006 | D7: AHUACATLÁN | E7: A
A8: 2026 | B8: 21 | C8: 007 | D8: AHUATLÁN | E8: A
A9: 2026 | B9: 21 | C9: 008 | D9: AHUAZOTEPEC | E9: A
A10: 2026 | B10: 21 | C10: 009 | D10: AHUEHUETITLA | E10: A
A11: 2026 | B11: 21 | C11: 010 | D11: AJALPAN | E11: A
A12: 2026 | B12: 21 | C12: 011 | D12: ALBINO ZERTUCHE | E12: A
A13: 2026 | B13: 21 | C13: 012 | D13: ALJOJUCA | E13: A
... A218: 2026 | B218: 21 | C218: 217 | D218: ZOQUITLÁN | E218: A

Sheet CATALOGO DE REGIONES
A1: EJERCICIO FISCAL | B1: REGIÓN | C1: DESCRIPCIÓN | D1: ESTATUS
A2: 2026 | B2: 01 | C2: XICOTEPEC | D2: A
A3: 2026 | B3: 02 | C3: HUAUCHINANGO | D3: A
A4: 2026 | B4: 03 | C4: CHIGNAHUAPAN | D4: A
A5: 2026 | B5: 04 | C5: CUAUTEMPAN | D5: A
A6: 2026 | B6: 05 | C6: ZACAPOAXTLA | D6: A
A7: 2026 | B7: 06 | C7: TEZIUTLÁN | D7: A
A8: 2026 | B8: 07 | C8: TLATLAUQUITEPEC | D8: A
A9: 2026 | B9: 08 | C9: LIBRES | D9: A
A10: 2026 | B10: 09 | C10: CIUDAD SERDÁN | D10: A
A11: 2026 | B11: 10 | C11: TECAMACHALCO | D11: A
A12: 2026 | B12: 11 | C12: ACATZINGO | D12: A
A13: 2026 | B13: 12 | C13: TEPEACA | D13: A
... A28: 2026 | B28: 27 | C28: AJALPAN | D28: A

Sheet CATALOGO DE PUEBLOS ORIGINARIOS
A1: EJERCICIO FISCAL | B1: PUEBLOS ORIGINARIOS | C1: DESCRIPCIÓN | D1: ESTATUS
A2: 2026 | B2: 01 | C2: MAZATECO | D2: A
A3: 2026 | B3: 02 | C3: MIXTECO | D3: A
A4: 2026 | B4: 03 | C4: NÁHUATL | D4: A
A5: 2026 | B5: 04 | C5: OTOMÍ | D5: A
A6: 2026 | B6: 05 | C6: POPOLOCA | D6: A
A7: 2026 | B7: 06 | C7: TEPEHUA | D7: A
A8: 2026 | B8: 07 | C8: TOTONACO | D8: A
